password_hashing/__init__.py
password_hashing/generatehash.py
password_hashing/passwordhash.py
password_hashing_python-0.3.0.dist-info/METADATA
password_hashing_python-0.3.0.dist-info/RECORD
password_hashing_python-0.3.0.dist-info/WHEEL
password_hashing_python-0.3.0.dist-info/top_level.txt
